{
    "menu": [
        {
            "id": 1,
            "name": "Caesar Salad",
            "category": "Appetizers",
            "image": "https://images.pexels.com/photos/2097090/pexels-photo-2097090.jpeg?auto=compress&cs=tinysrgb&w=1260&h=750&dpr=1",
            "ingredients": "Lettuce, croutons, parmesan, Caesar dressing",
            "price": 8.99
        },
        {
            "id": 2,
            "name": "Tomato Soup",
            "category": "Appetizers",
            "image": "https://images.pexels.com/photos/539451/pexels-photo-539451.jpeg?auto=compress&cs=tinysrgb&w=1260&h=750&dpr=1",
            "ingredients": "Tomatoes, cream, basil",
            "price": 5.99
        },
        {
            "id": 3,
            "name": "Bruschetta",
            "category": "Appetizers",
            "image": "https://images.pexels.com/photos/6126298/pexels-photo-6126298.jpeg?auto=compress&cs=tinysrgb&w=1260&h=750&dpr=1",
            "ingredients": "Bread, tomatoes, garlic, basil",
            "price": 6.5
        },
        {
            "id": 4,
            "name": "Grilled Salmon",
            "category": "Main Courses",
            "image": "https://images.pexels.com/photos/3763847/pexels-photo-3763847.jpeg?auto=compress&cs=tinysrgb&w=1260&h=750&dpr=1",
            "ingredients": "Salmon, lemon, herbs",
            "price": 15.99
        },
        {
            "id": 5,
            "name": "Spaghetti Bolognese",
            "category": "Main Courses",
            "image": "https://images.pexels.com/photos/6287539/pexels-photo-6287539.jpeg?auto=compress&cs=tinysrgb&w=300",
            "price": 12.99
        },
        {
            "id": 6,
            "name": "Margherita Pizza",
            "category": "Main Courses",
            "image": "https://images.pexels.com/photos/13814644/pexels-photo-13814644.jpeg?auto=compress&cs=tinysrgb&w=300",
            "ingredients": "Tomato, mozzarella, basil",
            "price": 10.99
        },
        {
            "id": 7,
            "name": "Chocolate Cake",
            "category": "Desserts",
            "image": "https://images.pexels.com/photos/1854652/pexels-photo-1854652.jpeg?auto=compress&cs=tinysrgb&w=1260&h=750&dpr=1",
            "ingredients": "Flour, cocoa, sugar, eggs",
            "price": 6.99
        },
        {
            "id": 8,
            "name": "Fruit Salad",
            "category": "Desserts",
            "image": "https://images.pexels.com/photos/3085148/pexels-photo-3085148.jpeg?auto=compress&cs=tinysrgb&w=1260&h=750&dpr=1",
            "ingredients": "Mixed fruits, mint",
            "price": 4.99
        },
        {
            "id": 9,
            "name": "Cheesecake",
            "category": "Desserts",
            "image": "https://images.pexels.com/photos/5852256/pexels-photo-5852256.jpeg?auto=compress&cs=tinysrgb&w=1260&h=750&dpr=1",
            "ingredients": "Cream cheese, graham crackers, sugar",
            "price": 7.99
        },
        {
            "id": 10,
            "name": "Ice Cream Sundae",
            "category": "Desserts",
            "image": "https://images.pexels.com/photos/9009957/pexels-photo-9009957.jpeg?auto=compress&cs=tinysrgb&w=1260&h=750&dpr=1",
            "ingredients": "Ice cream, chocolate syrup, nuts",
            "price": 5.5
        }
    ]
}